synochatbot/__init__.py
synochatbot/bot.py
synochatbot-2.8.dist-info/METADATA
synochatbot-2.8.dist-info/WHEEL
synochatbot-2.8.dist-info/top_level.txt
synochatbot-2.8.dist-info/RECORD
