Metadata-Version: 2.1
Name: synochatbot
Version: 2.8
Summary: A discord.py like thing but for synology chat
Home-page: UNKNOWN
Author: kokofixcomputers
License: UNKNOWN
Platform: UNKNOWN
Requires-Dist: flask ==3.0.3
Requires-Dist: requests ==2.31.0
